.gitignore
LICENSE
README.md
crisscross.py
setup.py
./scripts/crisscross
crisscross_py.egg-info/PKG-INFO
crisscross_py.egg-info/SOURCES.txt
crisscross_py.egg-info/dependency_links.txt
crisscross_py.egg-info/requires.txt
crisscross_py.egg-info/top_level.txt
examples/streams.py
examples/tcp_tunnel.py
scripts/crisscross