Metadata-Version: 2.1
Name: crisscross-py
Version: 1.0.4
Summary: Python Client for CrissCross Network
Home-page: https://github.com/SoCal-Software-Labs/crisscross_py
Author: Kyle Hanson
Author-email: kyle@statetrace.com
License: MIT
Platform: UNKNOWN
Classifier: Development Status :: 2 - Pre-Alpha
Classifier: Intended Audience :: Developers
Classifier: License :: OSI Approved :: MIT License
Classifier: Operating System :: OS Independent
Classifier: Programming Language :: Python
Classifier: Programming Language :: Python :: 3
Classifier: Programming Language :: Erlang
Classifier: Topic :: Software Development :: Libraries :: Python Modules
Classifier: Topic :: System :: Distributed Computing
